topdf/__init__.py
topdf/cmdline.py
topdf/mdtopdf.py
topdf/server.py
topdf/static/Monospace.ttf
topdf/static/index.html
xpdf-0.0.2.dist-info/METADATA
xpdf-0.0.2.dist-info/WHEEL
xpdf-0.0.2.dist-info/entry_points.txt
xpdf-0.0.2.dist-info/top_level.txt
xpdf-0.0.2.dist-info/RECORD
