Metadata-Version: 2.4
Name: xpdf
Version: 0.0.2
Summary: markdown to pdf
Author-email: Seven <1162584980@qq.com>
Maintainer-email: Seven <1162584980@qq.com>
License: MIT License
Classifier: License :: OSI Approved :: MIT License
Classifier: Environment :: Console :: Curses
Classifier: Operating System :: OS Independent
Classifier: Programming Language :: Python :: 3
Classifier: Topic :: Utilities
Requires-Python: >=3.11
Requires-Dist: click
Requires-Dist: types-click
Requires-Dist: markdown
Requires-Dist: weasyprint
Requires-Dist: pygments
Requires-Dist: fastapi
Requires-Dist: python-multipart
Requires-Dist: uvicorn
Requires-Dist: pydantic
Requires-Dist: pydantic-settings
Provides-Extra: dev
Requires-Dist: build; extra == "dev"
Requires-Dist: twine; extra == "dev"
